oclminify/__init__.py
oclminify/__main__.py
oclminify/build.py
oclminify/functions.py
oclminify/generator.py
oclminify/lexer.py
oclminify/minifier.py
oclminify/minify.py
oclminify/parser.py
oclminify-0.8.0.dist-info/DESCRIPTION.rst
oclminify-0.8.0.dist-info/METADATA
oclminify-0.8.0.dist-info/RECORD
oclminify-0.8.0.dist-info/WHEEL
oclminify-0.8.0.dist-info/entry_points.txt
oclminify-0.8.0.dist-info/metadata.json
oclminify-0.8.0.dist-info/top_level.txt
tests/__init__.py
tests/test_minifier.py
