Metadata-Version: 2.0
Name: oclminify
Version: 0.8.0
Summary: Minify OpenCL source files.
Home-page: https://github.com/StarByteSoftware/oclminify
Author: James Bendig
Author-email: jbendig@starbytesoftware.com
License: BSD
Platform: Cross Platform
Classifier: Development Status :: 4 - Beta
Classifier: Intended Audience :: Developers 
Classifier: License :: OSI Approved :: BSD License
Classifier: Programming Language :: Python :: 2
Classifier: Programming Language :: Python :: 3
Requires-Dist: pycparser (>=2.17)
Requires-Dist: pycparserext (>=2016.2)
Provides-Extra: build
Requires-Dist: PyOpenCL (>=2016.1); extra == 'build'
